{
  "title": "Culture Générale - Quiz 6",
  "category": "Culture Generale",
  "authorId": 1,
  "questions": [
    {
      "text": "Quel canal relie la mer Méditerranée à la mer Rouge ?",
      "options": ["Canal de Suez", "Canal de Panama", "Canal du Sinaï", "Canal du Karakoum"],
      "answer": "Canal de Suez"
    },
    {
      "text": "Un double magnum de champagne contient 3 litres.",
      "options": ["Vrai", "Faux"],
      "answer": "Vrai"
    },
    {
      "text": "Quelle montagne possède le plus haut sommet d'Europe ?",
      "options": ["Mont Elbrouz, Russie", "Chkhara, Géorgie", "Mont Ararat, Turquie", "Mont Blanc, France"],
      "answer": "Mont Elbrouz, Russie"
    },
    {
      "text": "Quel est le plus long pont du monde ?",
      "options": ["Grand pont de Danyang-Kunshan", "Chaussée du lac Pontchartrain", "Pont du marais de Manchac", "Pont de la baie de Hangzhou"],
      "answer": "Grand pont de Danyang-Kunshan"
    },
    {
      "text": "La baleine bleue est le plus grand animal ayant jamais vécu.",
      "options": ["Vrai", "Faux"],
      "answer": "Vrai"
    },
    {
      "text": "Qui détient le record du monde du 100 m sprint ?",
      "options": ["Usain Bolt", "Tyson Gay", "Yohan Blake", "Justin Gatlin"],
      "answer": "Usain Bolt"
    },
    {
      "text": "Quel est le plus grand organe du corps humain ?",
      "options": ["La peau", "Le foie", "Les poumons", "Le cerveau"],
      "answer": "La peau"
    },
    {
      "text": "Dans le jeu 'Cluedo', lequel de ces personnages n'est PAS jouable ?",
      "options": ["Professeur Violet", "Mademoiselle Rose", "Révérend Olive", "Madame Brunette"],
      "answer": "Madame Brunette"
    },
    {
      "text": "Le point d'exclamation était à l'origine utilisé comme symbole de question dans certaines langues.",
      "options": ["Vrai", "Faux"],
      "answer": "Faux"
    },
    {
      "text": "Quel est le nom de la monnaie utilisée au Japon ?",
      "options": ["Yen", "Won", "Yuan", "Ringgit"],
      "answer": "Yen"
    }
  ]
}